dep_scheduler/__init__.py
pyproject.toml
tests/__init__.py
tests/test_dep_module_scheduler.py
dep_module_scheduler-2.4.29.dist-info/WHEEL
dep_module_scheduler-2.4.29.dist-info/METADATA
dep_module_scheduler-2.4.29.dist-info/RECORD
