Metadata-Version: 2.1
Name: dep-module-scheduler
Version: 2.4.29
Summary: 
Author: everhide
Author-email: i.tolkachnikov@gmail.com
Requires-Python: >=3.9,<=3.11
Classifier: Programming Language :: Python :: 3
Classifier: Programming Language :: Python :: 3.9
Classifier: Programming Language :: Python :: 3.10
Classifier: Programming Language :: Python :: 3.11
Requires-Dist: APScheduler (>=3.9.1,<4.0.0)
Requires-Dist: dep-spec (>=2.3.29,<3.0.0)
Requires-Dist: poetry (==1.1.15)
